client/__init__.py
client/auth.py
client/memo.py
client/model.py
client/session.py
common/__init__.py
common/config.py
memos/__init__.py
memos/auth/__init__.py
memos/auth/signin.py
memos/auth/signout.py
memos/auth/whoami.py
memos/cli.py
memos/click_aliases.py
memos/echo.py
memos/edit.py
memos/list.py
memos/new.py
memos/remove.py
memos_cli-0.1.2.dist-info/LICENSE
memos_cli-0.1.2.dist-info/METADATA
memos_cli-0.1.2.dist-info/WHEEL
memos_cli-0.1.2.dist-info/entry_points.txt
memos_cli-0.1.2.dist-info/RECORD
