Metadata-Version: 2.1
Name: memos-cli
Version: 0.1.2
Summary: A CLI frontend for memos self-hosted memo hub
Author: Giulio De Matteis
Author-email: hello@giuliodematte.is
Requires-Python: >=3.11,<4.0
Classifier: Programming Language :: Python :: 3
Classifier: Programming Language :: Python :: 3.11
Requires-Dist: click (>=8.1.3,<9.0.0)
Requires-Dist: prettytable (>=3.7.0,<4.0.0)
Requires-Dist: requests (>=2.30.0,<3.0.0)
